{
  "cru": {
    "allowRejection": "false",
    "clock": "ttc",
    "cruId": "0xbf",
    "datapathMode": "packet",
    "loopback": "false",
    "gbtMode": "GBT",
    "downstreamData": "CTP",
    "ponUpstream": "true",
    "onuAddress": "0x5",
    "dynamicOffset": "true",
    "triggerWindowSize": "1000",
    "gbtEnabled": "true",
    "userLogicEnabled": "false",
    "runStatsEnabled": "false",
    "userAndCommonLogicEnabled": "false",
    "systemId": "0x20",
    "timeFrameLength": "128"
  },
  "links": {
    "enabled": "false",
    "gbtMux": "ttc",
    "feeId": "0x0"
  },
  "link0": {
    "enabled": "true",
    "gbtMux": "swt",
    "feeId": "0x2005"
  },
  "link1": {
    "enabled": "true",
    "gbtMux": "swt",
    "feeId": "0x2006"
  },
  "link2": {
    "enabled": "true",
    "gbtMux": "swt",
    "feeId": "0x2007"
  },
  "link3": {
    "enabled": "true",
    "gbtMux": "swt",
    "feeId": "0x2008"
  },
  "link4": {
    "enabled": "true",
    "gbtMux": "swt",
    "feeId": "0x2009"
  },
  "link5": {
    "enabled": "true",
    "gbtMux": "ttc",
    "feeId": "0x2105"
  },
  "link6": {
    "enabled": "true",
    "gbtMux": "ttc",
    "feeId": "0x2106"
  },
  "link7": {
    "enabled": "true",
    "gbtMux": "ttc",
    "feeId": "0x2107"
  },
  "link8": {
    "enabled": "true",
    "gbtMux": "ttc",
    "feeId": "0x2108"
  },
  "link9": {
    "enabled": "true",
    "gbtMux": "ttc",
    "feeId": "0x2109"
  },
  "link10": {
    "enabled": "true",
    "gbtMux": "ttc",
    "feeId": "0x2205"
  },
  "link11": {
    "enabled": "true",
    "gbtMux": "ttc",
    "feeId": "0x2206"
  }
}